mozanalysis/__init__.py
mozanalysis/bq.py
mozanalysis/config.py
mozanalysis/experiment.py
mozanalysis/exposure.py
mozanalysis/sizing.py
mozanalysis/utils.py
mozanalysis/bayesian_stats/__init__.py
mozanalysis/bayesian_stats/bayesian_bootstrap.py
mozanalysis/bayesian_stats/binary.py
mozanalysis/bayesian_stats/survival_func.py
mozanalysis/frequentist_stats/__init__.py
mozanalysis/frequentist_stats/bootstrap.py
mozanalysis/frequentist_stats/linear_models.py
mozanalysis/frequentist_stats/sample_size.py
mozanalysis/metrics/__init__.py
mozanalysis/metrics/desktop.py
mozanalysis/metrics/fenix.py
mozanalysis/metrics/firefox_ios.py
mozanalysis/metrics/focus_android.py
mozanalysis/metrics/focus_ios.py
mozanalysis/metrics/klar_android.py
mozanalysis/metrics/klar_ios.py
mozanalysis/segments/__init__.py
mozanalysis/segments/desktop.py
mozanalysis-2024.5.2.dist-info/LICENSE
mozanalysis-2024.5.2.dist-info/METADATA
mozanalysis-2024.5.2.dist-info/WHEEL
mozanalysis-2024.5.2.dist-info/top_level.txt
mozanalysis-2024.5.2.dist-info/RECORD
