Metadata-Version: 2.1
Name: mozanalysis
Version: 2024.5.2
Summary: A library for Mozilla experiments analysis
Home-page: https://github.com/mozilla/mozanalysis
Author: Mozilla Corporation
Author-email: fx-data-dev@mozilla.org
Requires-Python: >=3.10,<=3.11
License-File: LICENSE
Requires-Dist: attrs
Requires-Dist: mozilla-metric-config-parser >=2024.4.1
Requires-Dist: numpy
Requires-Dist: pandas
Requires-Dist: pyarrow
Requires-Dist: scipy
Requires-Dist: google-cloud-bigquery
Requires-Dist: google-cloud-bigquery-storage
Requires-Dist: statsmodels
Requires-Dist: marginaleffects ==0.0.11
Requires-Dist: matplotlib
Provides-Extra: docs
Requires-Dist: Sphinx ; extra == 'docs'
Requires-Dist: sphinx-autobuild ; extra == 'docs'
Requires-Dist: sphinx-rtd-theme ; extra == 'docs'
Provides-Extra: testing
Requires-Dist: mock ; extra == 'testing'
Requires-Dist: pytest ; extra == 'testing'
Requires-Dist: pytest-ruff ; extra == 'testing'
Requires-Dist: pytest-cov ; extra == 'testing'
Requires-Dist: pytest-timeout ; extra == 'testing'
Requires-Dist: ruff ==0.3.1 ; extra == 'testing'
